hvlbuzz/__init__.py
hvlbuzz/__main__.py
hvlbuzz/bundled_main.py
hvlbuzz/core.py
hvlbuzz/config/__init__.py
hvlbuzz/config/config.py
hvlbuzz/config/field_names.py
hvlbuzz/config/ini.py
hvlbuzz/export/__init__.py
hvlbuzz/export/csv.py
hvlbuzz/export/line_types.py
hvlbuzz/export/pdf.py
hvlbuzz/export/settings_data_rows.py
hvlbuzz/physics/__init__.py
hvlbuzz/physics/conductor.py
hvlbuzz/physics/line.py
hvlbuzz/physics/sound.py
hvlbuzz/physics/system.py
hvlbuzz/physics/tower.py
hvlbuzz/static/buzz.kv
hvlbuzz/ui/__init__.py
hvlbuzz/ui/dataclass_settings_panel.py
hvlbuzz/ui/gui_tools.py
hvlbuzz/ui/imagebutton.py
hvlbuzz/ui/layout.py
hvlbuzz/ui/main.py
hvlbuzz/ui/numeric_input.py
hvlbuzz/ui/plot.py
hvlbuzz/ui/config/__init__.py
hvlbuzz/ui/config/layout.py
hvlbuzz/ui/config/system.py
hvlbuzz/ui/config/systemaddpopup.py
hvlbuzz/ui/config/systemselector.py
hvlbuzz/ui/config/toolbar.py
hvlbuzz-2025.4.dist-info/licenses/LICENSE.txt
hvlbuzz-2025.4.dist-info/METADATA
hvlbuzz-2025.4.dist-info/WHEEL
hvlbuzz-2025.4.dist-info/entry_points.txt
hvlbuzz-2025.4.dist-info/top_level.txt
hvlbuzz-2025.4.dist-info/RECORD
