Metadata-Version: 2.4
Name: hvlbuzz
Version: 2025.4
Summary: Compute surface gradient of overhead power lines / prediction of audible noise and electromagnetic field at ground
Author-email: Aldo Tobler <faldo@student.ethz.ch>, Sören Hedtke <hedtkec@ethz.ch>, Pascal Bleuler <bleulerp@ethz.ch>, Henrik Menne <menne@fkh.ch>, Gerhard Bräunlich <g.braeunlich@disroot.org>
Maintainer-email: Henrik Menne <menne@fkh.ch>, Gerhard Bräunlich <g.braeunlich@disroot.org>
License: GNU GENERAL PUBLIC LICENSE
Project-URL: Repository, https://gitlab.com/ethz_hvl/hvlbuzz
Project-URL: Documentation, https://ethz_hvl.gitlab.io/hvlbuzz/
Keywords: high voltage,electro engineering
Classifier: Programming Language :: Python :: 3
Classifier: License :: OSI Approved :: GNU General Public License v3 (GPLv3)
Classifier: Operating System :: OS Independent
Requires-Python: >=3.9
License-File: LICENSE.txt
Requires-Dist: Kivy==2.1.0
Requires-Dist: kivy-garden.matplotlib
Requires-Dist: numpy<2.0,>=1.18
Requires-Dist: matplotlib==3.7.2
Requires-Dist: reportlab<4.0.0,>=3.5
Requires-Dist: pywin32>=1.0; platform_system == "Windows"
Requires-Dist: exceptiongroup; python_version < "3.11"
Provides-Extra: type-check
Requires-Dist: types-six; extra == "type-check"
Dynamic: license-file
